insper_mlops-0.2.0.dist-info/licenses/LICENSE
mlopstemplate/__init__.py
mlopstemplate/cli.py
mlopstemplate/config.py
mlopstemplate/core.py
insper_mlops-0.2.0.dist-info/METADATA
insper_mlops-0.2.0.dist-info/WHEEL
insper_mlops-0.2.0.dist-info/entry_points.txt
insper_mlops-0.2.0.dist-info/top_level.txt
insper_mlops-0.2.0.dist-info/RECORD
