Metadata-Version: 2.4
Name: insper-mlops
Version: 0.2.0
Summary: A command-line tool to standardize the creation of MLOps projects at Insper CDIA.
Author-email: Insper CDIA <cdia@insper.edu.br>
License-Expression: MIT
Project-URL: Homepage, https://github.com/centro-dados-ia/insper-mlops
Project-URL: Bug Tracker, https://github.com/centro-dados-ia/insper-mlops/issues
Classifier: Programming Language :: Python :: 3
Classifier: Operating System :: OS Independent
Classifier: Development Status :: 4 - Beta
Classifier: Intended Audience :: Developers
Classifier: Topic :: Software Development :: Build Tools
Requires-Python: >=3.8
License-File: LICENSE
Requires-Dist: GitPython
Requires-Dist: PyGithub>=2.0.0
Requires-Dist: typer[all]
Requires-Dist: requests
Dynamic: license-file
